post_processing_library_llm/__init__.py
post_processing_library_llm/get_metrics.py
post_processing_library_llm/ner.py
post_processing_library_llm-0.2.dist-info/METADATA
post_processing_library_llm-0.2.dist-info/WHEEL
post_processing_library_llm-0.2.dist-info/top_level.txt
post_processing_library_llm-0.2.dist-info/RECORD
